{
    "0-general": {
        "time": 222.0,
        "results": {
            "total_questions": 25,
            "correct": 25,
            "incorrect": 0,
            "failed_attempts": 1
        }
    },
    "1-VL-NA": {
        "time": 20.0,
        "results": {
            "total_questions": 3,
            "correct": 3,
            "incorrect": 0,
            "failed_attempts": 0
        }
    },
    "2-OS-ORD": {
        "time": 24.0,
        "results": {
            "total_questions": 3,
            "correct": 3,
            "incorrect": 0,
            "failed_attempts": 0
        }
    },
    "3-OS-DLG": {
        "time": 37.0,
        "results": {
            "total_questions": 3,
            "correct": 3,
            "incorrect": 0,
            "failed_attempts": 0
        }
    },
    "4-TE-NA": {
        "time": 43.0,
        "results": {
            "total_questions": 2,
            "correct": 2,
            "incorrect": 0,
            "failed_attempts": 0
        }
    },
    "5-OS-ASSOC": {
        "time": 24.0,
        "results": {
            "total_questions": 5,
            "correct": 5,
            "incorrect": 0,
            "failed_attempts": 0
        }
    },
    "6-TE-NA": {
        "time": 26.0,
        "results": {
            "total_questions": 2,
            "correct": 2,
            "incorrect": 0,
            "failed_attempts": 0
        }
    },
    "7-OS-ASSOC": {
        "time": 22.0,
        "results": {
            "total_questions": 4,
            "correct": 4,
            "incorrect": 0,
            "failed_attempts": 0
        }
    },
    "8-OS-PRON": {
        "time": 26.0,
        "results": {
            "total_questions": 3,
            "correct": 3,
            "incorrect": 0,
            "failed_attempts": 1
        }
    }
}