{
    "0-general": {
        "time": 169.0,
        "results": {
            "total_questions": 23,
            "correct": 23,
            "incorrect": 0,
            "failed_attempts": 0
        }
    },
    "1-OS-TRA": {
        "time": 31.0,
        "results": {
            "total_questions": 6,
            "correct": 6,
            "incorrect": 0,
            "failed_attempts": 0
        }
    },
    "2-OS-ORD": {
        "time": 36.0,
        "results": {
            "total_questions": 4,
            "correct": 4,
            "incorrect": 0,
            "failed_attempts": 0
        }
    },
    "3-OS-JOIN": {
        "time": 16.0,
        "results": {
            "total_questions": 4,
            "correct": 4,
            "incorrect": 0,
            "failed_attempts": 0
        }
    },
    "4-OS-ASSOC": {
        "time": 19.0,
        "results": {
            "total_questions": 4,
            "correct": 4,
            "incorrect": 0,
            "failed_attempts": 0
        }
    },
    "5-OS-DLG": {
        "time": 67.0,
        "results": {
            "total_questions": 5,
            "correct": 5,
            "incorrect": 0,
            "failed_attempts": 0
        }
    }
}